{
    "template": "account_preferences",
    "description": "Add preference to show adverts",
    "execution_order": 10,
    "enabled": true,
    "action": "str_replace",
    "find": "<xf:macro template=\"helper_account\" name=\"activity_privacy_row\" />",
    "replace": "\t\t\t<xf:checkboxrow label=\"{{ phrase('hampel_hideadverts_options') }}\">\n\t\t\t\t<xf:option name=\"option[show_adverts]\" checked=\"{$xf.visitor.Option.show_adverts}\"\n\t\t\t\t\tlabel=\"{{ phrase('hampel_hideadverts_show_adverts') }}\" \n\t\t\t\t\thint=\"{{ phrase('hampel_hideadverts_show_adverts_hint') }}\" />\n\t\t\t</xf:checkboxrow>\n\n$0"
}